{"mc":{"attack":{"frameRate":12,"frames":[{"res":"10043","x":-93,"y":-237},{"res":"10044","x":-173,"y":-192},{"res":"10045","x":-154,"y":-194},{"res":"10046","x":-114,"y":-234},{"res":"10047","x":-91,"y":-139},{"res":"10048","x":-163,"y":-159},{"res":"10049","x":-137,"y":-149},{"res":"10050","x":-77,"y":-137}]},"hit":{"frameRate":1,"frames":[{"res":"10051","x":-72,"y":-151}]}},"res":{"10043":{"x":632,"y":2,"w":184,"h":178},"10044":{"x":1234,"y":2,"w":206,"h":164},"10045":{"x":1026,"y":2,"w":206,"h":168},"10046":{"x":818,"y":2,"w":206,"h":168},"10047":{"x":150,"y":2,"w":132,"h":218},"10048":{"x":444,"y":2,"w":186,"h":184},"10049":{"x":284,"y":2,"w":158,"h":200},"10050":{"x":2,"y":2,"w":146,"h":226},"10051":{"x":1442,"y":2,"w":232,"h":140}}}