{"mc":{
	"pet1053_3r":{
		"frameRate":12,
		"frames":[
			{"res":"30009","x":-125,"y":-192},
			{"res":"30010","x":-125,"y":-191},
			{"res":"30011","x":-125,"y":-176},
			{"res":"30012","x":-124,"y":-172},
			{"res":"30013","x":-120,"y":-170},
			{"res":"30014","x":-116,"y":-189},
			{"res":"30015","x":-114,"y":-192},
			{"res":"30016","x":-123,"y":-191}
		]
}},
"res":{
	"30009":{"x":400,"y":2,"w":202,"h":180},
	"30010":{"x":2,"y":2,"w":202,"h":184},
	"30011":{"x":1002,"y":2,"w":202,"h":168},
	"30012":{"x":1206,"y":2,"w":202,"h":164},
	"30013":{"x":1410,"y":2,"w":200,"h":162},
	"30014":{"x":806,"y":2,"w":194,"h":180},
	"30015":{"x":206,"y":2,"w":192,"h":182},
	"30016":{"x":604,"y":2,"w":200,"h":180}
}}