{"mc":{
	"pet1064_1s":{
		"frameRate":12,
		"frames":[
			{"res":"10001","x":-84,"y":-147},
			{"res":"10002","x":-83,"y":-147},
			{"res":"10003","x":-84,"y":-147},
			{"res":"10004","x":-84,"y":-145},
			{"res":"10005","x":-81,"y":-146},
			{"res":"10006","x":-82,"y":-146},
			{"res":"10007","x":-83,"y":-147},
			{"res":"10008","x":-83,"y":-147}
		]
}},
"res":{
	"10001":{"x":552,"y":2,"w":136,"h":176},
	"10002":{"x":414,"y":2,"w":136,"h":176},
	"10003":{"x":274,"y":2,"w":138,"h":176},
	"10004":{"x":962,"y":2,"w":138,"h":174},
	"10005":{"x":826,"y":2,"w":134,"h":176},
	"10006":{"x":138,"y":2,"w":134,"h":178},
	"10007":{"x":2,"y":2,"w":134,"h":178},
	"10008":{"x":690,"y":2,"w":134,"h":176}
}}