{"mc":{
	"pet1079_3r":{
		"frameRate":12,
		"frames":[
			{"res":"30009","x":-132,"y":-170},
			{"res":"30010","x":-123,"y":-151},
			{"res":"30011","x":-113,"y":-148},
			{"res":"30012","x":-114,"y":-156},
			{"res":"30013","x":-123,"y":-179},
			{"res":"30014","x":-131,"y":-204},
			{"res":"30015","x":-133,"y":-226},
			{"res":"30016","x":-131,"y":-218}
		]
}},
"res":{
	"30009":{"x":948,"y":2,"w":242,"h":160},
	"30010":{"x":1650,"y":2,"w":254,"h":146},
	"30011":{"x":1414,"y":2,"w":234,"h":148},
	"30012":{"x":1192,"y":2,"w":220,"h":160},
	"30013":{"x":718,"y":2,"w":228,"h":186},
	"30014":{"x":480,"y":2,"w":236,"h":210},
	"30015":{"x":2,"y":2,"w":238,"h":228},
	"30016":{"x":242,"y":2,"w":236,"h":214}
}}