{"mc":{
	"pet1080_3r":{
		"frameRate":12,
		"frames":[
			{"res":"30009","x":-136,"y":-167},
			{"res":"30010","x":-139,"y":-165},
			{"res":"30011","x":-138,"y":-171},
			{"res":"30012","x":-135,"y":-172},
			{"res":"30013","x":-137,"y":-175},
			{"res":"30014","x":-139,"y":-175},
			{"res":"30015","x":-136,"y":-170},
			{"res":"30016","x":-132,"y":-168}
		]
}},
"res":{
	"30009":{"x":1722,"y":2,"w":238,"h":206},
	"30010":{"x":1242,"y":2,"w":244,"h":214},
	"30011":{"x":754,"y":2,"w":242,"h":228},
	"30012":{"x":250,"y":2,"w":238,"h":234},
	"30013":{"x":2,"y":2,"w":246,"h":242},
	"30014":{"x":490,"y":2,"w":262,"h":232},
	"30015":{"x":998,"y":2,"w":242,"h":226},
	"30016":{"x":1488,"y":2,"w":232,"h":214}
}}