{"mc":{
	"pet1001_3s":{
		"frameRate":12,
		"frames":[
			{"res":"30001","x":-52,"y":-65},
			{"res":"30002","x":-50,"y":-63},
			{"res":"30003","x":-50,"y":-65},
			{"res":"30004","x":-48,"y":-67},
			{"res":"30005","x":-48,"y":-67},
			{"res":"30006","x":-50,"y":-67},
			{"res":"30007","x":-52,"y":-67},
			{"res":"30008","x":-54,"y":-67}
		]
}},
"res":{
	"30001":{"x":544,"y":2,"w":108,"h":80},
	"30002":{"x":762,"y":2,"w":106,"h":78},
	"30003":{"x":654,"y":2,"w":106,"h":80},
	"30004":{"x":438,"y":2,"w":104,"h":82},
	"30005":{"x":332,"y":2,"w":104,"h":82},
	"30006":{"x":224,"y":2,"w":106,"h":82},
	"30007":{"x":114,"y":2,"w":108,"h":82},
	"30008":{"x":2,"y":2,"w":110,"h":82}
}}