{"mc":{
	"pet4102_3s":{
		"frameRate":12,
		"frames":[
			{"res":"30001","x":-65,"y":-129},
			{"res":"30002","x":-73,"y":-129},
			{"res":"30003","x":-75,"y":-129},
			{"res":"30004","x":-79,"y":-128},
			{"res":"30005","x":-75,"y":-128},
			{"res":"30006","x":-71,"y":-128},
			{"res":"30007","x":-69,"y":-128},
			{"res":"30008","x":-65,"y":-130}
		]
}},
"res":{
	"30001":{"x":2,"y":988,"w":92,"h":142},
	"30002":{"x":2,"y":422,"w":100,"h":142},
	"30003":{"x":2,"y":142,"w":102,"h":140},
	"30004":{"x":2,"y":2,"w":106,"h":138},
	"30005":{"x":2,"y":284,"w":102,"h":136},
	"30006":{"x":2,"y":566,"w":98,"h":136},
	"30007":{"x":2,"y":704,"w":96,"h":138},
	"30008":{"x":2,"y":844,"w":92,"h":142}
}}