{"mc":{
	"wing017_3p":{
		"frameRate":12,
		"frames":[
			{"res":"30027","x":-155,"y":-265},
			{"res":"30028","x":-156,"y":-264},
			{"res":"30029","x":-155,"y":-260},
			{"res":"30030","x":-155,"y":-261},
			{"res":"30031","x":-155,"y":-262},
			{"res":"30032","x":-154,"y":-262},
			{"res":"30033","x":-154,"y":-262},
			{"res":"30034","x":-154,"y":-264}
		]
}},
"res":{
	"30027":{"x":554,"y":270,"w":272,"h":266},
	"30028":{"x":278,"y":268,"w":274,"h":266},
	"30029":{"x":2,"y":538,"w":270,"h":260},
	"30030":{"x":278,"y":2,"w":276,"h":264},
	"30031":{"x":2,"y":270,"w":274,"h":266},
	"30032":{"x":2,"y":2,"w":274,"h":266},
	"30033":{"x":278,"y":536,"w":272,"h":264},
	"30034":{"x":556,"y":2,"w":270,"h":266}
}}