{"mc":{
	"wing017_1p":{
		"frameRate":12,
		"frames":[
			{"res":"10027","x":-143,"y":-248},
			{"res":"10028","x":-138,"y":-249},
			{"res":"10029","x":-137,"y":-245},
			{"res":"10030","x":-136,"y":-247},
			{"res":"10031","x":-138,"y":-248},
			{"res":"10032","x":-136,"y":-248},
			{"res":"10033","x":-136,"y":-246},
			{"res":"10034","x":-138,"y":-247}
		]
}},
"res":{
	"10027":{"x":2,"y":2,"w":218,"h":280},
	"10028":{"x":222,"y":2,"w":210,"h":280},
	"10029":{"x":1476,"y":2,"w":208,"h":276},
	"10030":{"x":1060,"y":2,"w":204,"h":278},
	"10031":{"x":434,"y":2,"w":206,"h":280},
	"10032":{"x":642,"y":2,"w":204,"h":280},
	"10033":{"x":1266,"y":2,"w":208,"h":276},
	"10034":{"x":848,"y":2,"w":210,"h":278}
}}