{"mc":{
	"clothes1005_3o":{
		"frameRate":12,
		"frames":[
			{"res":"30035","x":-55,"y":-176},
			{"res":"30036","x":-58,"y":-174},
			{"res":"30037","x":-61,"y":-171},
			{"res":"30038","x":-64,"y":-168},
			{"res":"30039","x":-64,"y":-165},
			{"res":"30040","x":-63,"y":-168},
			{"res":"30041","x":-61,"y":-170},
			{"res":"30042","x":-59,"y":-174}
		]
}},
"res":{
	"30035":{"x":2,"y":984,"w":96,"h":140},
	"30036":{"x":2,"y":842,"w":100,"h":140},
	"30037":{"x":2,"y":560,"w":106,"h":138},
	"30038":{"x":2,"y":280,"w":112,"h":138},
	"30039":{"x":2,"y":2,"w":114,"h":136},
	"30040":{"x":2,"y":140,"w":112,"h":138},
	"30041":{"x":2,"y":420,"w":108,"h":138},
	"30042":{"x":2,"y":700,"w":102,"h":140}
}}