{"mc":{"attack":{"frameRate":12,"frames":[{"res":"10043","x":-66,"y":-154},{"res":"10044","x":-59,"y":-146},{"res":"10045","x":-64,"y":-160},{"res":"10046","x":-66,"y":-166},{"res":"10047","x":-65,"y":-162},{"res":"10048","x":-66,"y":-158},{"res":"10049","x":-66,"y":-160},{"res":"10050","x":-67,"y":-166}]},"hit":{"frameRate":1,"frames":[{"res":"10051","x":-64,"y":-162}]}},"res":{"10043":{"x":2,"y":854,"w":102,"h":132},"10044":{"x":2,"y":1130,"w":98,"h":124},"10045":{"x":2,"y":714,"w":108,"h":138},"10046":{"x":2,"y":140,"w":112,"h":144},"10047":{"x":2,"y":286,"w":112,"h":140},"10048":{"x":2,"y":2,"w":114,"h":136},"10049":{"x":2,"y":428,"w":112,"h":138},"10050":{"x":2,"y":568,"w":108,"h":144},"10051":{"x":2,"y":988,"w":100,"h":140}}}