{"mc":{
	"cj_fs_06":{
		"frameRate":12,
		"frames":[
			{"res":"10001","x":-137,"y":-296},
			{"res":"10002","x":-137,"y":-300},
			{"res":"10003","x":-137,"y":-291},
			{"res":"10004","x":-138,"y":-293},
			{"res":"10005","x":-137,"y":-295},
			{"res":"10006","x":-137,"y":-300},
			{"res":"10007","x":-137,"y":-299},
			{"res":"10008","x":-137,"y":-300}
		]
}},
"res":{
	"10001":{"x":262,"y":310,"w":258,"h":304},
	"10002":{"x":522,"y":2,"w":258,"h":306},
	"10003":{"x":2,"y":618,"w":258,"h":298},
	"10004":{"x":262,"y":616,"w":260,"h":300},
	"10005":{"x":522,"y":310,"w":258,"h":302},
	"10006":{"x":262,"y":2,"w":258,"h":306},
	"10007":{"x":2,"y":310,"w":258,"h":306},
	"10008":{"x":2,"y":2,"w":258,"h":306}
}}