{"mc":{
	"pet1013_s":{
		"frameRate":12,
		"frames":[
			{"res":"00001","x":-90,"y":-173},
			{"res":"00002","x":-90,"y":-173},
			{"res":"00003","x":-91,"y":-173},
			{"res":"00004","x":-92,"y":-170},
			{"res":"00005","x":-94,"y":-170},
			{"res":"00006","x":-93,"y":-169},
			{"res":"00007","x":-93,"y":-171},
			{"res":"00008","x":-92,"y":-173}
		]
}},
"res":{
	"00001":{"x":426,"y":2,"w":138,"h":176},
	"00002":{"x":286,"y":2,"w":138,"h":176},
	"00003":{"x":144,"y":2,"w":140,"h":176},
	"00004":{"x":856,"y":2,"w":142,"h":174},
	"00005":{"x":566,"y":2,"w":144,"h":174},
	"00006":{"x":1000,"y":2,"w":142,"h":172},
	"00007":{"x":712,"y":2,"w":142,"h":174},
	"00008":{"x":2,"y":2,"w":140,"h":176}
}}