{"mc":{
	"ui_fs_10":{
		"frameRate":12,
		"frames":[
			{"res":"00001","x":-174,"y":-373},
			{"res":"00002","x":-174,"y":-371},
			{"res":"00003","x":-174,"y":-369},
			{"res":"00004","x":-174,"y":-371},
			{"res":"00005","x":-174,"y":-371},
			{"res":"00006","x":-174,"y":-373},
			{"res":"00007","x":-174,"y":-374},
			{"res":"00008","x":-174,"y":-372}
		]
}},
"res":{
	"00001":{"x":2,"y":2,"w":314,"h":502},
	"00002":{"x":634,"y":2,"w":314,"h":500},
	"00003":{"x":950,"y":502,"w":314,"h":496},
	"00004":{"x":950,"y":2,"w":314,"h":498},
	"00005":{"x":2,"y":506,"w":314,"h":496},
	"00006":{"x":318,"y":2,"w":314,"h":500},
	"00007":{"x":634,"y":504,"w":314,"h":498},
	"00008":{"x":318,"y":504,"w":314,"h":498}
}}